{
  "$comment": "Golden fixture: .ferros-log from an alias session. Use this to test the claim flow — importing on a home device should merge 15 XP per entry into the profile.",
  "ferrosVersion": "1.0",
  "logType": "alias-session",
  "alias": {
    "id": "tesla",
    "name": "Nikola Tesla",
    "icon": "⚡",
    "class": "Engineer",
    "attribution": "unlinked"
  },
  "sessionStart": "2026-04-10T14:00:00.000Z",
  "sessionEnd": "2026-04-10T15:30:00.000Z",
  "entries": [
    {
      "ts": "2026-04-10T14:05:00.000Z",
      "text": "Started deep work session on circuit design",
      "type": "activity",
      "seal": null
    },
    {
      "ts": "2026-04-10T14:45:00.000Z",
      "text": "Completed prototype wiring diagram",
      "type": "activity",
      "seal": null
    },
    {
      "ts": "2026-04-10T15:20:00.000Z",
      "text": "Reviewed calculations and filed notes",
      "type": "activity",
      "seal": null
    }
  ],
  "entryCount": 3,
  "claimInstructions": "Import this file on your home FERROS instance to claim these logs and merge them into your profile. Unlinked until claimed."
}
